{
  "RestaurantName": "Kantakortteli",
  "RestaurantUrl": "https://www.foodandco.fi/ravintolat/Ravintolat-kaupungeittain/oulu/kantakortteli/",
  "PriceHeader": null,
  "Footer": "Huomioithan, että ravintolassa käytetyt raaka-aineet saattavat vaihtua suunnitellusta ja siten verkkosivuilla julkaistut dieettimerkinnät ja tuoteselosteet voivat poiketa todellisesta tarjonnasta. Kehotamme allergisia henkilöitä aina tarkastamaan tarjotun ruuan soveltuvuus omaan ruokavalioon ravintolassa. Kiitos ymmärryksestänne.",
  "MenusForDays": [
    {
      "Date": "2022-09-23T00:00:00+00:00",
      "LunchTime": "10.30- 14.00, Wicked Rabbit 10.30-13.30",
      "SetMenus": [
        {
          "SortOrder": 0,
          "Name": "Kasvislounas",
          "Price": "Amk 2,70 / Lounasbuffet 10,90",
          "Components": [
            "Soija-kasvislasagnea (A ,VS)"
          ]
        },
        {
          "SortOrder": 0,
          "Name": "Lounas",
          "Price": "Amk 2,70",
          "Components": [
            "Kuhapyöryköitä (A ,L ,M)",
            "Sinappirelishkermaviilikastiketta (A ,G ,L)",
            "Annanperunoita (A ,G ,ILM ,L ,M ,Veg)"
          ]
        },
        {
          "SortOrder": 0,
          "Name": "Lounas erikoishintainen",
          "Price": "Amk 5,30",
          "Components": [
            "Pulled chicken -hampurilainen (A ,L ,VS)",
            "Ranskalaisia perunoita (G ,ILM ,L ,M ,Veg)"
          ]
        },
        {
          "SortOrder": 0,
          "Name": "Jälkiruoka",
          "Price": "Amk 1,60",
          "Components": [
            "Päärynä-jogurttipannacottaa (A ,G ,L)"
          ]
        },
        {
          "SortOrder": 0,
          "Name": "Wicked Rabbit kasvisruoka",
          "Price": null,
          "Components": [
            "Pinaatti-ricottacanneloneja (A ,VS)",
            "Pastajuustoraastetta (A ,G ,L)"
          ]
        },
        {
          "SortOrder": 0,
          "Name": "Wicked Rabbit  vegaani kasvisruoka",
          "Price": null,
          "Components": [
            "Punajuurikuorrutettua tofua (A ,G ,ILM ,L ,M ,Veg)"
          ]
        },
        {
          "SortOrder": 0,
          "Name": "Wicked Rabbit lämmin lisäke",
          "Price": null,
          "Components": [
            "Peruna-juuressärää (* ,G ,ILM ,L ,M ,Veg)"
          ]
        },
        {
          "SortOrder": 0,
          "Name": "Wicked Rabbit kasviskeitto",
          "Price": null,
          "Components": [
            "Valkopapusosekeittoa (* ,A ,G ,ILM ,L ,M ,Veg)"
          ]
        }
      ]
    },
    {
      "Date": "2022-09-24T00:00:00+00:00",
      "LunchTime": null,
      "SetMenus": []
    },
    {
      "Date": "2022-09-25T00:00:00+00:00",
      "LunchTime": null,
      "SetMenus": []
    }
  ],
  "ErrorText": null
}