{
  "RestaurantName": "Dipoli",
  "RestaurantUrl": "https://www.foodandco.fi/ravintolat/Ravintolat-kaupungeittain/espoo/dipoli/",
  "PriceHeader": null,
  "Footer": "Ravintolamme on kelan ateriatuen piirissä 2,30 €/ ateria. Opiskelijahintaisen aterian edellytyksenä on voimassa oleva opiskelijakortti.\n\nHuomioithan, että ravintolassa käytetyt raaka-aineet saattavat vaihtua suunnitellusta ja siten verkkosivuilla julkaistut dieettimerkinnät ja tuoteselosteet voivat poiketa todellisesta tarjonnasta. Kehotamme allergisia henkilöitä aina tarkastamaan tarjotun ruuan soveltuvuus omaan ruokavalioon ravintolassa. Kiitos ymmärryksestänne.\n\nHyvää ruokahalua!",
  "MenusForDays": [
    {
      "Date": "2022-09-08T00:00:00+00:00",
      "LunchTime": "11.00-15.00",
      "SetMenus": [
        {
          "SortOrder": 0,
          "Name": "Vegaaninen kasvislounas",
          "Price": "2,70€ / 6,50€ / 9,30€",
          "Components": [
            "Intialaista sieni-kookoscurrya (* ,G ,ILM ,L ,M ,Veg ,VS)"
          ]
        },
        {
          "SortOrder": 21,
          "Name": "Lounas I",
          "Price": "2,70€ / 6,50€ / 9,30€",
          "Components": [
            "Seitifilettä intialaisittain (* ,A ,G ,L)",
            "Keitettyjä perunoita (* ,A ,G ,ILM ,L ,M ,Veg)"
          ]
        },
        {
          "SortOrder": 22,
          "Name": "Lounas  II",
          "Price": "2,70€ / 6,50€ / 9,30€",
          "Components": [
            "Broileria hedelmäkastikkeessa (* ,A ,G ,L)",
            "Höyrytettyä tummaa riisiä (* ,G ,L ,M ,Veg)"
          ]
        },
        {
          "SortOrder": 29,
          "Name": "Grillistä",
          "Price": "5,30€ / 8,50€ / 11,50€",
          "Components": [
            "Kauden kasviksia (G ,L ,M ,Veg)",
            "Porsaanleike, paprikaa ja sipulia (A ,L ,M)",
            "Porkkana-perunasosetta (A ,G ,ILM ,L)"
          ]
        },
        {
          "SortOrder": 30,
          "Name": "Grillistä",
          "Price": "5,30€ / 8,50€ / 11,50€",
          "Components": [
            "Halloumjuusto-kirsikkatomaattipizza (A)"
          ]
        },
        {
          "SortOrder": 100,
          "Name": "Jälkiruoka",
          "Price": "1,40€",
          "Components": [
            "Pannukakkua (A ,L)",
            "Mansikkahilloa (G ,L ,M ,Veg)",
            "Kermavaahtoa (A ,G ,L)"
          ]
        }
      ]
    },
    {
      "Date": "2022-09-09T00:00:00+00:00",
      "LunchTime": "11.00 - 15.00",
      "SetMenus": [
        {
          "SortOrder": 13,
          "Name": "Kasvislounas",
          "Price": "2,70€ / 6,50€ / 9,30€",
          "Components": [
            "Herne-kasvispihvejä (A ,L ,M)",
            "Harissalla maustettua jogurttikastiketta (A ,G ,ILM ,L)",
            "Paahdettuja uuniperunoita (* ,G ,ILM ,L ,M ,Veg)"
          ]
        },
        {
          "SortOrder": 21,
          "Name": "Lounas I",
          "Price": "2,70€ / 6,50€ / 9,30€",
          "Components": [
            "Kaalikääryleitä (* ,G ,L ,M)",
            "Ruskeaa kastiketta (A ,ILM ,L)",
            "Paahdettuja uuniperunoita (* ,G ,ILM ,L ,M ,Veg)"
          ]
        },
        {
          "SortOrder": 22,
          "Name": "Lounas  II",
          "Price": "2,70€ / 6,50€ / 9,30€",
          "Components": [
            "Kalkkuna-juustokastiketta (* ,A ,G ,L)",
            "Luomutäysjyväkierrepastaa (* ,A ,ILM ,L ,M ,Veg)"
          ]
        },
        {
          "SortOrder": 100,
          "Name": "Jälkiruoka",
          "Price": "1,40€",
          "Components": [
            "Kaakaomoussea (G ,L ,M ,Veg)"
          ]
        }
      ]
    },
    {
      "Date": "2022-09-10T00:00:00+00:00",
      "LunchTime": "Suljettu",
      "SetMenus": []
    },
    {
      "Date": "2022-09-11T00:00:00+00:00",
      "LunchTime": "Suljettu",
      "SetMenus": []
    }
  ],
  "ErrorText": null
}