{
  "RestaurantName": "Kahvila Kvarkki",
  "RestaurantUrl": "https://www.semma.fi/ravintolat2/ylistonrinne/kahvila-kvarkki/",
  "PriceHeader": null,
  "Footer": "Vegaani ja gluteeniton vaihtoehto saatavilla päivittäin! Kysy lisätietoja henkilökunnaltamme.",
  "MenusForDays": [
    {
      "Date": "2022-09-14T00:00:00+00:00",
      "LunchTime": null,
      "SetMenus": [
        {
          "SortOrder": 0,
          "Name": null,
          "Price": "2,70 / 5,20 / 5,80 / 7,90",
          "Components": [
            "Mustapapupihvi (* ,G ,ILM ,L ,M ,Veg ,VS)",
            "Kurkkusalsaa (* ,A ,G ,ILM ,L ,M ,Veg ,VS)",
            "Papas arrugadas -perunoita (* ,G ,ILM ,L ,M ,Veg)"
          ]
        },
        {
          "SortOrder": 0,
          "Name": null,
          "Price": null,
          "Components": [
            "Kasvis-kaalikeittoa (* ,A ,G ,ILM ,L ,M ,Veg)"
          ]
        },
        {
          "SortOrder": 0,
          "Name": "LOUNAS",
          "Price": "2,70 / 5,20 / 5,80 / 7,90",
          "Components": [
            "Jauhelihapizzaa (A ,L ,VS)"
          ]
        },
        {
          "SortOrder": 0,
          "Name": "JÄLKIRUOKA",
          "Price": "1,20",
          "Components": [
            "Päärynä-jogurttipannacottaa (A ,G ,L)",
            "Hedelmäsalaattia (G ,L ,M ,Veg)"
          ]
        }
      ]
    },
    {
      "Date": "2022-09-15T00:00:00+00:00",
      "LunchTime": null,
      "SetMenus": [
        {
          "SortOrder": 0,
          "Name": null,
          "Price": "2,70 / 5,20 / 5,80 / 7,90",
          "Components": [
            "Kookos-kasviscurrya luomutofulla (* ,A ,G ,ILM ,L ,M ,Veg ,VS)",
            "Höyrytettyä tummaa riisiä (* ,G ,L ,M ,Veg)"
          ]
        },
        {
          "SortOrder": 0,
          "Name": "KEITTOLOUNAS",
          "Price": "2,70 / 5,20 / 5,80 / 7,90",
          "Components": [
            "Kukkakaalisosekeittoa (* ,A ,G ,ILM ,L)"
          ]
        },
        {
          "SortOrder": 0,
          "Name": "LOUNAS",
          "Price": "2,70 / 5,20 / 5,80 / 7,90",
          "Components": [
            "Jauhelihapihvejä ja metsäsienikastiketta (* ,A ,L)",
            "Paahdettuja uuniperunoita (* ,G ,ILM ,L ,M ,Veg)"
          ]
        },
        {
          "SortOrder": 0,
          "Name": "JÄLKIRUOKA",
          "Price": "1,20",
          "Components": [
            "Suklaamoussea (A ,G ,L)"
          ]
        }
      ]
    },
    {
      "Date": "2022-09-16T00:00:00+00:00",
      "LunchTime": null,
      "SetMenus": [
        {
          "SortOrder": 0,
          "Name": null,
          "Price": "2,70 / 5,20 / 5,80 / 7,90",
          "Components": [
            "Kasviskroketteja (G ,ILM ,L ,M ,Veg ,VS)",
            "Paholaisenhilloa (* ,A ,G ,ILM ,L ,M ,Veg)",
            "Paahdettuja uuniperunoita (* ,G ,ILM ,L ,M ,Veg)"
          ]
        },
        {
          "SortOrder": 0,
          "Name": "LOUNAS",
          "Price": "2,70 / 5,20 / 5,80 / 7,90",
          "Components": [
            "Broileria currykastikkeessa (* ,A ,G ,L)",
            "Höyrytettyä tummaa riisiä (* ,G ,L ,M ,Veg)"
          ]
        },
        {
          "SortOrder": 0,
          "Name": "LOUNAS",
          "Price": "3,90 / 6,30 / 7,10 / 8,10",
          "Components": [
            "Briossihampurilainen rotukarjapihvi ja pekoni (A ,L ,M)",
            "Paahdettuja uuniperunoita (* ,G ,ILM ,L ,M ,Veg)",
            "Chilimajoneesia (A ,G ,L)"
          ]
        },
        {
          "SortOrder": 0,
          "Name": "JÄLKIRUOKA",
          "Price": "1,20",
          "Components": [
            "Ananas-omenakiisseliä (G ,L ,M ,Veg)",
            "Kauravaahtoa (A ,G ,L ,M ,Veg)"
          ]
        }
      ]
    },
    {
      "Date": "2022-09-17T00:00:00+00:00",
      "LunchTime": null,
      "SetMenus": []
    },
    {
      "Date": "2022-09-18T00:00:00+00:00",
      "LunchTime": null,
      "SetMenus": []
    }
  ],
  "ErrorText": null
}