{
  "RestaurantName": "Ravintola Maija",
  "RestaurantUrl": "https://www.semma.fi/ravintolat2/mattilanniemi/maija/",
  "PriceHeader": null,
  "Footer": "Vegaaninen ja gluteeniton vaihtoehto saatavilla päivittäin! Kysy lisätietoja henkilökunnaltamme.\nHyvää ruokahalua!",
  "MenusForDays": [
    {
      "Date": "2022-08-22T00:00:00+00:00",
      "LunchTime": "10.30-14.00",
      "SetMenus": [
        {
          "SortOrder": 0,
          "Name": "KASVISLOUNAS",
          "Price": "2,70 / 5,80 /7,90",
          "Components": [
            "Quornia currykastikkeessa (* ,A ,G ,ILM ,L)"
          ]
        },
        {
          "SortOrder": 0,
          "Name": "LOUNAS",
          "Price": "2,70 / 5,80 /7,90",
          "Components": [
            "Broileria teriyakikastikkeessa (* ,A ,G ,ILM ,L ,M ,VS)"
          ]
        },
        {
          "SortOrder": 0,
          "Name": "LOUNAS",
          "Price": "2,70 / 5,80/7,90",
          "Components": [
            "Jauhelihapyöryköitä (* ,A ,L ,M)"
          ]
        },
        {
          "SortOrder": 0,
          "Name": "KEITTOLOUNAS",
          "Price": "2,70 / 5,80/7,90",
          "Components": [
            "Meksikolaista makkarakeittoa (* ,A ,G ,L ,M ,VS)"
          ]
        },
        {
          "SortOrder": 0,
          "Name": "JÄLKIRUOKA",
          "Price": "1,20",
          "Components": [
            "Mangosmoothie (A ,G ,L)"
          ]
        }
      ]
    },
    {
      "Date": "2022-08-23T00:00:00+00:00",
      "LunchTime": "10.30-14.00",
      "SetMenus": [
        {
          "SortOrder": 0,
          "Name": "KASVISLOUNAS",
          "Price": "2,70 / 5,80 /7,90",
          "Components": [
            "Soija-kauratäytteiset paprikat (* ,A ,ILM ,L ,M ,Veg)"
          ]
        },
        {
          "SortOrder": 0,
          "Name": "KEITTOLOUNAS",
          "Price": "2,70 / 5,80 /7,90",
          "Components": [
            "Porkkanasosekeittoa (* ,A ,G ,ILM ,L)"
          ]
        },
        {
          "SortOrder": 0,
          "Name": "LOUNAS",
          "Price": "2,70 / 5,80/7,90",
          "Components": [
            "Rapeita kalapaloja (* ,A ,L ,M)"
          ]
        },
        {
          "SortOrder": 0,
          "Name": "LOUNAS",
          "Price": "5,20 / 8,80 /9,10",
          "Components": [
            "Paneroitua broileria (G ,L ,M)",
            "Bearnaisekastiketta (A ,G)"
          ]
        },
        {
          "SortOrder": 0,
          "Name": "JÄLKIRUOKA",
          "Price": "1,20",
          "Components": [
            "Omena-kanelirahkaa (A ,G ,L)"
          ]
        }
      ]
    },
    {
      "Date": "2022-08-24T00:00:00+00:00",
      "LunchTime": "10.30-14.00",
      "SetMenus": [
        {
          "SortOrder": 0,
          "Name": "KASVISLOUNAS",
          "Price": "2,70 / 5,80 /7,90",
          "Components": [
            "Feta-pinaatti-cashewpähkinäpizzaa (A ,VL)"
          ]
        },
        {
          "SortOrder": 0,
          "Name": "LOUNAS",
          "Price": "2,70 / 5,80 /7,90",
          "Components": [
            "Broilerinugetteja (A ,L ,M)"
          ]
        },
        {
          "SortOrder": 0,
          "Name": "LOUNAS",
          "Price": "2,70 / 5,80/7,90",
          "Components": [
            "Chilimaustettua porsaspataa (* ,A ,G ,L ,M ,VS)"
          ]
        },
        {
          "SortOrder": 0,
          "Name": "KEITTOLOUNAS",
          "Price": "2,70 / 5,80/7,90",
          "Components": [
            "Kaali-jauhelihakeittoa (* ,A ,G ,L ,M)"
          ]
        },
        {
          "SortOrder": 0,
          "Name": "JÄLKIRUOKA",
          "Price": "1,20",
          "Components": [
            "Tyrni-jogurttipannacottaa (A ,G ,L)"
          ]
        }
      ]
    },
    {
      "Date": "2022-08-25T00:00:00+00:00",
      "LunchTime": "10.30-14.00",
      "SetMenus": [
        {
          "SortOrder": 0,
          "Name": "KASVISLOUNAS",
          "Price": "2,70 / 5,80 /7,90",
          "Components": [
            "Porkkana-pestolasagnea (* ,A ,L ,VS)"
          ]
        },
        {
          "SortOrder": 0,
          "Name": "LOUNAS",
          "Price": "2,70 / 5,80 /7,90",
          "Components": [
            "Uunimakkaraa juustokuorrutteella (A ,G ,L)"
          ]
        },
        {
          "SortOrder": 0,
          "Name": "LOUNAS",
          "Price": "2,70 / 5,80/7,90",
          "Components": [
            "Broileria currykastikkeessa (* ,A ,G ,L)"
          ]
        },
        {
          "SortOrder": 0,
          "Name": "KEITTOLOUNAS",
          "Price": "2,70 / 5,80/7,90",
          "Components": [
            "Kalkkuna-kasviskeittoa (* ,A ,G ,ILM ,L)"
          ]
        },
        {
          "SortOrder": 0,
          "Name": "JÄLKIRUOKA",
          "Price": "4,00 €",
          "Components": [
            "Jälkiruokapöytä (sis. kahvi/tee) ()"
          ]
        }
      ]
    },
    {
      "Date": "2022-08-26T00:00:00+00:00",
      "LunchTime": "10.30-14.00",
      "SetMenus": [
        {
          "SortOrder": 0,
          "Name": "KASVISLOUNAS",
          "Price": "2,70 / 5,80 /7,90",
          "Components": [
            "Kasviskroketteja (G ,ILM ,L ,M ,Veg ,VS)"
          ]
        },
        {
          "SortOrder": 0,
          "Name": "LOUNAS",
          "Price": "2,70 / 5,80/7,90",
          "Components": [
            "Talon jauhelihapihvi ja metsäsienikastiketta (A ,L)"
          ]
        },
        {
          "SortOrder": 0,
          "Name": "KEITTOLOUNAS",
          "Price": "2,70 / 5,80/7,90",
          "Components": [
            "Kirjolohikeittoa (* ,A ,G ,ILM ,L)"
          ]
        },
        {
          "SortOrder": 0,
          "Name": "LOUNAS",
          "Price": "4,40 /7,10 /9,10",
          "Components": [
            "Burgeriperjantai ()"
          ]
        }
      ]
    },
    {
      "Date": "2022-08-27T00:00:00+00:00",
      "LunchTime": null,
      "SetMenus": []
    },
    {
      "Date": "2022-08-28T00:00:00+00:00",
      "LunchTime": null,
      "SetMenus": []
    }
  ],
  "ErrorText": null
}