{
  "RestaurantName": "Ravintola Maija",
  "RestaurantUrl": "https://www.semma.fi/ravintolat2/mattilanniemi/maija/",
  "PriceHeader": null,
  "Footer": "Vegaaninen ja gluteeniton vaihtoehto saatavilla päivittäin! Kysy lisätietoja henkilökunnaltamme.\nHyvää ruokahalua!",
  "MenusForDays": [
    {
      "Date": "2024-10-01T00:00:00+00:00",
      "LunchTime": "10.30-14.30",
      "SetMenus": [
        {
          "SortOrder": 0,
          "Name": "KASVISLOUNAS",
          "Price": "2,95 /6,30 /8,40",
          "Components": [
            "Seitanpataa Stifado (*, A, ILM, L, M, Veg, VS)"
          ]
        },
        {
          "SortOrder": 0,
          "Name": "LOUNAS",
          "Price": "2,95 /6,30 /8,40",
          "Components": [
            "Kinkkukiusausta (*, A, G, ILM, L)"
          ]
        },
        {
          "SortOrder": 0,
          "Name": "KEITTOLOUNAS",
          "Price": "2,95 /6,30 /8,40",
          "Components": [
            "Täyteläistä broilerikeittoa (*, A, G, ILM, L)"
          ]
        },
        {
          "SortOrder": 0,
          "Name": "LOUNAS",
          "Price": "5,60 / 9,30 /9,60",
          "Components": [
            "Paahdettua kirjolohta teriyakikastikkeessa (*, A, G, ILM, L, M, VS)",
            "Satokauden kasviksia (G, L, M, Veg)"
          ]
        }
      ]
    },
    {
      "Date": "2024-10-02T00:00:00+00:00",
      "LunchTime": "10.30-14.30",
      "SetMenus": [
        {
          "SortOrder": 0,
          "Name": "KASVISLOUNAS",
          "Price": "2,95 /6,30 /8,40",
          "Components": [
            "Vönerpannupizzaa (A, ILM, L)"
          ]
        },
        {
          "SortOrder": 0,
          "Name": "KEITTOLOUNAS",
          "Price": "2,95 /6,30 /8,40",
          "Components": [
            "Kasvisminestronea (*, A, ILM, L, M, Veg, VS)"
          ]
        },
        {
          "SortOrder": 0,
          "Name": "LOUNAS",
          "Price": "2,95 /6,30 /8,40",
          "Components": [
            "Sinappista porsaspataa (*, A, L)"
          ]
        },
        {
          "SortOrder": 0,
          "Name": "LOUNAS",
          "Price": "2,95 /6,30 /8,40",
          "Components": [
            "Broileripyöryköitä (*, A, L, M)",
            "Currykastiketta (*, A, ILM, L)"
          ]
        }
      ]
    },
    {
      "Date": "2024-10-03T00:00:00+00:00",
      "LunchTime": "10.30-14.30",
      "SetMenus": [
        {
          "SortOrder": 0,
          "Name": "KASVISLOUNAS",
          "Price": "2,95 /6,30 /8,40",
          "Components": [
            "Härkistä ja paahdettuja kasviksia teriyakiakastikkeessa (*, A, G, ILM, L, M, Veg)"
          ]
        },
        {
          "SortOrder": 0,
          "Name": "KEITTOLOUNAS",
          "Price": "2,95 /6,30 /8,40",
          "Components": [
            "Kasvis-hernekeittoa (*, A, G, ILM, L, M, Veg)"
          ]
        },
        {
          "SortOrder": 0,
          "Name": "LOUNAS",
          "Price": "2,95 /6,30 /8,40",
          "Components": [
            "Rapeaa seitifilettä (*, A, ILM, L, M)",
            "Ruohosipulijogurttia (*, A, G, ILM, L)"
          ]
        },
        {
          "SortOrder": 0,
          "Name": "KEITTOLOUNAS",
          "Price": "2,95 /6,30 /8,40",
          "Components": [
            "Perinteistä hernekeittoa (*, A, G, ILM, L, M)"
          ]
        }
      ]
    },
    {
      "Date": "2024-10-04T00:00:00+00:00",
      "LunchTime": "10.30-14.30",
      "SetMenus": [
        {
          "SortOrder": 0,
          "Name": "KASVISLOUNAS",
          "Price": "2,95 /6,30 /8,40",
          "Components": [
            "Falafelpihvejä (G, ILM, L, M, Veg)",
            "Sambal Oelek -gurttia (*, A, G, ILM, L, M, Veg)"
          ]
        },
        {
          "SortOrder": 0,
          "Name": "LOUNAS",
          "Price": "2,95 /6,30 /8,40",
          "Components": [
            "Broileria Madras Chicken (*, A, G, ILM, L, VS)"
          ]
        },
        {
          "SortOrder": 0,
          "Name": "KEITTOLOUNAS",
          "Price": "2,95 /6,30 /8,40",
          "Components": [
            "Kalakeittoa (*, A, G, ILM, L)"
          ]
        },
        {
          "SortOrder": 0,
          "Name": "BURGERI",
          "Price": "5,60 /9,30 /9,60",
          "Components": [
            "Burgeri perjantai ()"
          ]
        }
      ]
    },
    {
      "Date": "2024-10-05T00:00:00+00:00",
      "LunchTime": null,
      "SetMenus": []
    },
    {
      "Date": "2024-10-06T00:00:00+00:00",
      "LunchTime": null,
      "SetMenus": []
    }
  ],
  "ErrorText": null
}