{
  "RestaurantName": "Ravintola Uno",
  "RestaurantUrl": "https://www.semma.fi/ravintolat2/ruusupuisto/ravintola-uno/",
  "PriceHeader": null,
  "Footer": "Vegaani ja gluteeniton vaihtoehto saatavilla päivittäin! Kysy lisätietoja henkilökunnaltamme.",
  "MenusForDays": [
    {
      "Date": "2024-06-05T00:00:00+00:00",
      "LunchTime": "10.30–14.00",
      "SetMenus": [
        {
          "SortOrder": 0,
          "Name": "KASVISLOUNAS",
          "Price": "2,95 / 5,70 / 6,30 / 8,40",
          "Components": [
            "Pinaattiohukaisia (*, A, ILM, L)",
            "Puolukkahilloa (G, L, M, Veg)"
          ]
        },
        {
          "SortOrder": 0,
          "Name": "KASVISLOUNAS",
          "Price": "2,95 / 5,70 / 6,30 / 8,40",
          "Components": [
            "Chili sin carnea (*, A, ILM, L, M, Veg)"
          ]
        },
        {
          "SortOrder": 0,
          "Name": "KEITTOLOUNAS",
          "Price": "2,95 / 5,70 / 6,30 / 8,40",
          "Components": [
            "Aasialaista lohi-seitikeittoa (*, A, G, ILM, L, M)"
          ]
        },
        {
          "SortOrder": 0,
          "Name": "",
          "Price": null,
          "Components": []
        }
      ]
    },
    {
      "Date": "2024-06-06T00:00:00+00:00",
      "LunchTime": "10.30–14.00",
      "SetMenus": [
        {
          "SortOrder": 0,
          "Name": "KASVISLOUNAS",
          "Price": "2,95 / 5,70 / 6,30 / 8,40",
          "Components": [
            "Talon porkkana-lehtikaalipihvejä (A, ILM, L, M, Veg)",
            "Basilikakermaviilikastiketta (A, G, ILM, L)"
          ]
        },
        {
          "SortOrder": 0,
          "Name": "KASVISLOUNAS",
          "Price": "2,95 / 5,70 / 6,30 / 8,40",
          "Components": [
            "Härkis-kasviskastiketta (*, A, ILM, L, M, Veg)"
          ]
        },
        {
          "SortOrder": 0,
          "Name": "KEITTOLOUNAS",
          "Price": "2,95 / 5,70 / 6,30 / 8,40",
          "Components": [
            "Nakkikeittoa (*, A, G, L, M)"
          ]
        },
        {
          "SortOrder": 0,
          "Name": "PAISTOPISTELOUNAS LINJASTA",
          "Price": "5,60/8,30/9,30/9,60",
          "Components": [
            "Paahdettua broileria (G, L, M)",
            "Currykermaviilikastiketta (A, G, L)",
            "Papas arrugadas -perunoita (*, G, ILM, L, M, Veg)"
          ]
        },
        {
          "SortOrder": 0,
          "Name": "",
          "Price": null,
          "Components": []
        }
      ]
    },
    {
      "Date": "2024-06-07T00:00:00+00:00",
      "LunchTime": "10.30–14.00",
      "SetMenus": [
        {
          "SortOrder": 0,
          "Name": "KASVISLOUNAS",
          "Price": "2,95 / 5,70 / 6,30 / 8,40",
          "Components": [
            "Soija-kauratäytteiset paprikat  *, A, ILM, L, M, Veg ()"
          ]
        },
        {
          "SortOrder": 0,
          "Name": "KEITTOLOUNAS",
          "Price": "2,95 / 5,70 / 6,30 / 8,40",
          "Components": [
            "Bataattisosekeittoa (*, A, G, ILM, L)"
          ]
        },
        {
          "SortOrder": 0,
          "Name": "LOUNAS",
          "Price": "2,95 / 5,70 / 6,30 / 8,40",
          "Components": [
            "Kotimaisia kirjolohipyöryköitä (A, ILM, L)",
            "Tilli-kermaviilikastiketta (A, G, L)",
            "Keitettyjä perunoita (*, A, G, ILM, L, M, Veg)"
          ]
        },
        {
          "SortOrder": 0,
          "Name": "",
          "Price": null,
          "Components": [
            "Amerikansalaattia (G, L, M, Veg)",
            "Punakaali-puolukkasalaattia (A, G, L, M, Veg)",
            "Pinaatti-pestopastasalaattia (A, L, VS)",
            "Basilikamarinoituja papuja (A, ILM, L, M, Veg)",
            "Kauden kasvis (G, L, M, Veg)",
            "Leipäpöytä (kg) ()",
            "Ruokajuoma (kg) ()"
          ]
        }
      ]
    },
    {
      "Date": "2024-06-08T00:00:00+00:00",
      "LunchTime": null,
      "SetMenus": []
    },
    {
      "Date": "2024-06-09T00:00:00+00:00",
      "LunchTime": null,
      "SetMenus": []
    }
  ],
  "ErrorText": null
}