{
  "RestaurantName": "Ravintola Ylistö",
  "RestaurantUrl": "https://www.semma.fi/ravintolat2/ylistonrinne/ravintola-ylisto/",
  "PriceHeader": null,
  "Footer": "Vegaani ja gluteeniton vaihtoehto saatavilla päivittäin! Kysy lisätietoja henkilökunnaltamme.",
  "MenusForDays": [
    {
      "Date": "2023-06-16T00:00:00+00:00",
      "LunchTime": "10.30–14.00",
      "SetMenus": [
        {
          "SortOrder": 0,
          "Name": "VEGAANINEN KASVISLOUNAS",
          "Price": "2,95 / 5,70 / 6,30 / 8,40",
          "Components": [
            "Tofu-kasviswokkia (*, A, G, ILM, L, M, Veg)"
          ]
        },
        {
          "SortOrder": 0,
          "Name": "LOUNAS",
          "Price": "2,95 / 5,70 / 6,30 / 8,40",
          "Components": [
            "Seitimurekepihvi (*, A, G, L, M)"
          ]
        },
        {
          "SortOrder": 0,
          "Name": "LOUNAS",
          "Price": "5,60 / 8,30 / 9,20 / 10,20",
          "Components": [
            "Porsaan grillipihvi (*, G, L, M)",
            "Punaviinikastiketta (G, L, M, VS)",
            "Juustoperunaa (A, G, L)"
          ]
        }
      ]
    },
    {
      "Date": "2023-06-17T00:00:00+00:00",
      "LunchTime": null,
      "SetMenus": []
    },
    {
      "Date": "2023-06-18T00:00:00+00:00",
      "LunchTime": null,
      "SetMenus": []
    }
  ],
  "ErrorText": null
}