{
  "RestaurantName": "Ravintola Rentukka",
  "RestaurantUrl": "https://www.semma.fi/ravintolat2/muut/ravintola-rentukka/",
  "PriceHeader": null,
  "Footer": "Vegaani ja gluteeniton vaihtoehto pyydett채ess채.",
  "MenusForDays": [
    {
      "Date": "2024-11-10T00:00:00+00:00",
      "LunchTime": "12:00 - 15:00",
      "SetMenus": [
        {
          "SortOrder": 0,
          "Name": "VEGAANINEN KASVISLOUNAS",
          "Price": "2,95/8,50",
          "Components": [
            "Seitania tomaatti-valkosipulikastikkeessa (*, A, ILM, L, M, Veg, VS)",
            "Tummaa riisi채 (*, G, L, M, Veg)"
          ]
        },
        {
          "SortOrder": 0,
          "Name": "",
          "Price": null,
          "Components": []
        },
        {
          "SortOrder": 1,
          "Name": "KASVISLOUNAS",
          "Price": "2,95/8,50",
          "Components": [
            "Halloumi-kasvispataa ja lehtipinaattia (*, A, ILM)",
            "Paahdettua perunaa (*, G, ILM, L, M, Veg)"
          ]
        },
        {
          "SortOrder": 2,
          "Name": "LOUNAS",
          "Price": "2,95/8,50",
          "Components": [
            "Ruotsalaista pyttipannua (A, G, L)"
          ]
        },
        {
          "SortOrder": 5,
          "Name": "PAISTOPISTE",
          "Price": "5,60/10,50",
          "Components": [
            "Porsaan grillipihvi채 (*, G, L, M)",
            "Bearnaisea (A, G)",
            "Paahdettuja lohkoperunoita (*, G, ILM, L, M, Veg)",
            "Satokauden kasviksia (G, L, M, Veg)"
          ]
        }
      ]
    }
  ],
  "ErrorText": null
}